CHANGES.txt
README.txt
TODO.txt
setup.py
bda/__init__.py
bda.resultduplexer.egg-info/PKG-INFO
bda.resultduplexer.egg-info/SOURCES.txt
bda.resultduplexer.egg-info/dependency_links.txt
bda.resultduplexer.egg-info/entry_points.txt
bda.resultduplexer.egg-info/namespace_packages.txt
bda.resultduplexer.egg-info/not-zip-safe
bda.resultduplexer.egg-info/requires.txt
bda.resultduplexer.egg-info/top_level.txt
bda/resultduplexer/__init__.py
bda/resultduplexer/attopicpatch.py
bda/resultduplexer/configure.zcml
bda/resultduplexer/contentproxy.py
bda/resultduplexer/exampleduplexer.py
bda/resultduplexer/interfaces.py
bda/resultduplexer/profiles.zcml
bda/resultduplexer/skins.zcml
bda/resultduplexer/browser/__init__.py
bda/resultduplexer/browser/configure.zcml
bda/resultduplexer/browser/duplexer.py
bda/resultduplexer/browser/interfaces.py
bda/resultduplexer/browser/resultduplexer/livesearch_reply.py
bda/resultduplexer/browser/resultduplexer/queryCatalog.py
bda/resultduplexer/profiles/default/metadata.xml
bda/resultduplexer/profiles/default/skins.xml