Metadata-Version: 1.0
Name: bda.resultduplexer
Version: 1.0-beta2
Summary: module providing duplexing of search results in plone.
Home-page: UNKNOWN
Author: Robert Niedereiter
Author-email: rnix@squarewave.at
License: General Public Licence
Platform: UNKNOWN
Classifier: Development Status :: 4 - Beta
Classifier: Environment :: Web Environment
Classifier: Framework :: Zope2
Classifier: License :: OSI Approved :: GNU General Public License (GPL)
Classifier: Operating System :: OS Independent
Classifier: Programming Language :: Python
Classifier: Topic :: Internet :: WWW/HTTP :: Dynamic Content
